nvtl_cli/__init__.py
nvtl_cli/constants.py
nvtl_cli/login.py
nvtl_cli/nvtl.py
nvtl_cli/cli_actions/__init__.py
nvtl_cli/cli_actions/actions.py
nvtl_cli/cli_actions/network_click_wrapper.py
nvidia_transfer_learning_client-5.3.0.dist-info/LICENSE
nvidia_transfer_learning_client-5.3.0.dist-info/METADATA
nvidia_transfer_learning_client-5.3.0.dist-info/WHEEL
nvidia_transfer_learning_client-5.3.0.dist-info/entry_points.txt
nvidia_transfer_learning_client-5.3.0.dist-info/top_level.txt
nvidia_transfer_learning_client-5.3.0.dist-info/RECORD
